MANIFEST.in
README.md
setup.py
dikbm_adapter/__init__.py
dikbm_adapter/client.py
dikbm_adapter/main.py
dikbm_adapter/settings.py
python_dikbm_adapter.egg-info/PKG-INFO
python_dikbm_adapter.egg-info/SOURCES.txt
python_dikbm_adapter.egg-info/dependency_links.txt
python_dikbm_adapter.egg-info/entry_points.txt
python_dikbm_adapter.egg-info/not-zip-safe
python_dikbm_adapter.egg-info/requires.txt
python_dikbm_adapter.egg-info/top_level.txt