Metadata-Version: 1.0
Name: python-dikbm-adapter
Version: 0.1.1
Summary: DiKBM adapter to send request to RSA web service
Home-page: http://github.com/suvit/python-dikbm-adapter
Author: Victor Safronovich
Author-email: vsafronovich@gmail.com
License: MIT
Platform: UNKNOWN
